publish_lib_ghp/__init__.py
publish_lib_ghp/greeting.py
publish_lib_ghp/operations.py
publish_lib_ghp-0.2.8.dist-info/METADATA
publish_lib_ghp-0.2.8.dist-info/WHEEL
publish_lib_ghp-0.2.8.dist-info/licenses/LICENSE
publish_lib_ghp-0.2.8.dist-info/RECORD
