Metadata-Version: 2.4
Name: publish-lib-ghp
Version: 0.2.8
Summary: A simple Python library demonstrating how to publish packages to PyPI
License: MIT
License-File: LICENSE
Keywords: python,library,example,pypi,packaging
Author: Gabriel Henrique Pascon
Author-email: gh.pascon@gmail.com
Requires-Python: >=3.11,<4.0
Classifier: Development Status :: 4 - Beta
Classifier: Intended Audience :: Developers
Classifier: License :: OSI Approved :: MIT License
Classifier: Operating System :: OS Independent
Classifier: Programming Language :: Python :: 3
Classifier: Programming Language :: Python :: 3.11
Classifier: Programming Language :: Python :: 3.12
Classifier: Programming Language :: Python :: 3.13
Classifier: Programming Language :: Python :: 3.14
Classifier: Topic :: Software Development :: Libraries :: Python Modules
Classifier: Typing :: Typed
Project-URL: Documentation, https://github.com/ghpascon/publish_lib_ghp#readme
Project-URL: Homepage, https://github.com/ghpascon/publish_lib_ghp
Project-URL: Repository, https://github.com/ghpascon/publish_lib_ghp
